{
  "attemptId": "ATTEMPT-20260403-0HF6",
  "executionCheck": {
    "runner": "codex-exec",
    "availability": "degraded",
    "passed": false,
    "issues": [
      "codex exec exited with code 2."
    ],
    "exitCode": 2,
    "failedToStart": false
  },
  "staticCheck": {
    "passed": false,
    "issues": [
      "Static checks were skipped because execution did not complete successfully."
    ]
  },
  "runtimeCheck": {
    "passed": false,
    "issues": []
  },
  "semanticCheck": {
    "verdict": "not-evaluated",
    "criteria": []
  },
  "qualification": {
    "verdict": "unqualified",
    "issues": [
      {
        "code": "runner-failed",
        "message": "codex exec exited with code 2."
      }
    ]
  },
  "hasRetryableFailures": true
}
